odoo/addons/account_payment_sale/README.rst
odoo/addons/account_payment_sale/__init__.py
odoo/addons/account_payment_sale/__manifest__.py
odoo/addons/account_payment_sale/i18n/account_payment_sale.pot
odoo/addons/account_payment_sale/i18n/ca.po
odoo/addons/account_payment_sale/i18n/da_DK.po
odoo/addons/account_payment_sale/i18n/de.po
odoo/addons/account_payment_sale/i18n/es.po
odoo/addons/account_payment_sale/i18n/es_AR.po
odoo/addons/account_payment_sale/i18n/fr.po
odoo/addons/account_payment_sale/i18n/fr_FR.po
odoo/addons/account_payment_sale/i18n/hr.po
odoo/addons/account_payment_sale/i18n/it.po
odoo/addons/account_payment_sale/i18n/nl.po
odoo/addons/account_payment_sale/i18n/nl_NL.po
odoo/addons/account_payment_sale/i18n/pt_BR.po
odoo/addons/account_payment_sale/i18n/sl.po
odoo/addons/account_payment_sale/i18n/sv.po
odoo/addons/account_payment_sale/i18n/zh_CN.po
odoo/addons/account_payment_sale/models/__init__.py
odoo/addons/account_payment_sale/models/sale_order.py
odoo/addons/account_payment_sale/models/sale_report.py
odoo/addons/account_payment_sale/readme/CONTRIBUTORS.md
odoo/addons/account_payment_sale/readme/DESCRIPTION.md
odoo/addons/account_payment_sale/readme/USAGE.md
odoo/addons/account_payment_sale/static/description/icon.png
odoo/addons/account_payment_sale/static/description/index.html
odoo/addons/account_payment_sale/tests/__init__.py
odoo/addons/account_payment_sale/tests/common.py
odoo/addons/account_payment_sale/tests/test_sale_order.py
odoo/addons/account_payment_sale/views/sale_order_view.xml
odoo/addons/account_payment_sale/views/sale_report_templates.xml
odoo_addon_account_payment_sale-19.0.1.0.1.dist-info/METADATA
odoo_addon_account_payment_sale-19.0.1.0.1.dist-info/WHEEL
odoo_addon_account_payment_sale-19.0.1.0.1.dist-info/top_level.txt
odoo_addon_account_payment_sale-19.0.1.0.1.dist-info/RECORD
